README.rst
setup.cfg
setup.py
httpmeter/__init__.py
httpmeter/__main__.py
httpmeter/cli.py
httpmeter/net.py
httpmeter/stats.py
httpmeter/utils.py
httpmeter.egg-info/PKG-INFO
httpmeter.egg-info/SOURCES.txt
httpmeter.egg-info/dependency_links.txt
httpmeter.egg-info/entry_points.txt
httpmeter.egg-info/requires.txt
httpmeter.egg-info/top_level.txt