Metadata-Version: 1.1
Name: httpmeter
Version: 0.1.0
Summary: Hackable HTTP benchmarking tool.
Home-page: https://github.com/povilasb/httpmeter
Author: Povilas Balciunas
Author-email: balciunas90@gmail.com
License: MIT
Platform: UNKNOWN
Classifier: Programming Language :: Python :: 3.5
Classifier: Operating System :: POSIX :: Linux
Classifier: Natural Language :: English
Classifier: Development Status :: 3 - Alpha
